__init__.py
py_request_nacos/__init__.py
py_request_nacos/example.py
py_request_nacos-0.0.11.dist-info/LICENSE
py_request_nacos-0.0.11.dist-info/METADATA
py_request_nacos-0.0.11.dist-info/WHEEL
py_request_nacos-0.0.11.dist-info/top_level.txt
py_request_nacos-0.0.11.dist-info/RECORD
